explorer/__init__.py
explorer/explorer.py
explorer/services/__init__.py
explorer/services/gateway/__init__.py
explorer/services/gateway/gateway.py
explorer/services/template/__init__.py
explorer/services/template/template.py
hub/__init__.py
hub/hub.py
hub/log/__init__.py
hub/log/log.py
hub/manager/__init__.py
hub/manager/manager.py
hub/network/__init__.py
hub/network/network.py
hub/protocol/__init__.py
hub/protocol/protocol.py
hub/services/__init__.py
hub/services/broadcast/__init__.py
hub/services/broadcast/broadcast.py
hub/services/gateway/__init__.py
hub/services/gateway/gateway.py
hub/services/ota/__init__.py
hub/services/ota/ota.py
hub/services/rrpc/__init__.py
hub/services/rrpc/rrpc.py
hub/services/shadow/__init__.py
hub/services/shadow/shadow.py
hub/utils/__init__.py
hub/utils/codec.py
hub/utils/providers.py
tencent_iot_device-1.0.0.dist-info/METADATA
tencent_iot_device-1.0.0.dist-info/WHEEL
tencent_iot_device-1.0.0.dist-info/top_level.txt
tencent_iot_device-1.0.0.dist-info/RECORD
