Metadata-Version: 2.1
Name: tencent-iot-device
Version: 1.0.0
Summary: Tencent IoT Explorer SDK for Python
Home-page: https://github.com/tencentyun/iot-device-python
Author: larrytin
Author-email: dev_tester@163.com
License: UNKNOWN
Platform: UNKNOWN
Classifier: Programming Language :: Python :: 3
Classifier: License :: OSI Approved :: MIT License
Classifier: Operating System :: OS Independent
